Workbook

Sheet Store Projections
A1: Hardware | C1: Starter Pack | E1: Stores number Location | F1: Stores number Achat | I1: Store count
A2: 1018 | C2: 0 | E2: 7 | F2: 0 | I2: 3
A8: Location | I8: Achat
B9: Location mensuel | D9: 180 | J9: Achat | L9: 1800
J10: App | L10: 50
D16: Brut | E16: Net | F16: ROI | L16: Brut | M16: Net | N16: ROI
A17: Par an | D17: =(D9*E2)*12+(A2*E2) -> 22246 | E17: =(D17-(A2*E2))+C2 -> 15120 | F17: =A2/D9 -> 5.6555556 | I17: Par an | L17: =(L9*F2)+((L10*12)*F2)+C2 -> 0 | M17: =L17-A2 -> -1018 | N17: =I2/L9 -> 0.0016666667
A18: 2 ans | D18: =(D9*E2)*24 -> 30240 | E18: =D18 -> 30240 | I18: 2 ans | L18: =(L9*F2)+((L10*12)*F2)+C2 -> 0 | M18: =L18 -> 0
A19: 3 ans | D19: =(D9*E2)*36 -> 45360 | E19: =D19 -> 45360 | I19: 3 ans | L19: =(L9*F2)+((L10*12)*F2)+C2 -> 0 | M19: =L19 -> 0
A20: 4 ans | D20: =(D9*E2)*48 -> 60480 | E20: =D20 -> 60480 | I20: 4 ans | L20: =(L9*F2)+((L10*12)*F2)+C2 -> 0 | M20: =L20 -> 0
A21: 5 ans | D21: =(D9*E2)*60 -> 75600 | E21: =D21 -> 75600 | I21: 5 ans | L21: =(L9*F2)+((L10*12)*F2)+C2 -> 0 | M21: =L21 -> 0
D24: =SUM(D17:D21) -> 233926 | E24: =SUM(E17:E21) -> 226800 | L24: =SUM(L17:L21) -> 0 | M24: =SUM(M17:M21) -> -1018
I25: 10 ans
A26: 10 ans | E26: =E24*2 -> 453600
I28: =E24+M24 -> 225782

Sheet Hardware Total
A1: Hardware
A3: Product Code | C3: Product Name | F3: Quantity | G3: Buy | I3: Sell | K3: Cost total | M3: Net value | O3: Total value | Q3: Total net value
A4: AKSP-21 | C4: Kiosk 21.5 | F4: ='Hardware O''Comptoir'!F4+'Hardware CuzCup'!F4 -> 3 | G4: 500 | I4: 1699.99 | K4: =F4*G4 -> 1500 | M4: =I4-G4 -> 1199.99 | O4: =F4*I4 -> 5099.97 | Q4: =F4*M4 -> 3599.97
A5: AKSP-27 | C5: Kiosk 27 | F5: 0 | G5: 680 | I5: 2100 | K5: =F5*G5 -> 0 | M5: =I5-G5 -> 1420 | O5: =F5*I5 -> 0 | Q5: =F5*M5 -> 0
A6: AKSP-32 | C6: Kiosk 32 | F6: ='Hardware O''Comptoir'!F6+'Hardware CuzCup'!F6 -> 3 | G6: 800 | I6: 2799.99 | K6: =F6*G6 -> 2400 | M6: =I6-G6 -> 1999.99 | O6: =F6*I6 -> 8399.97 | Q6: =F6*M6 -> 5999.97
A7: PW-02 | C7: Imprimante | F7: ='Hardware O''Comptoir'!F7+'Hardware CuzCup'!F7 -> 2 | G7: 80 | I7: 179.88 | K7: =F7*G7 -> 160 | M7: =I7-G7 -> 99.88 | O7: =F7*I7 -> 359.76 | Q7: =F7*M7 -> 199.76
A8: AT-11 | C8: Tablette 11 pouces | F8: ='Hardware O''Comptoir'!F8+'Hardware CuzCup'!F8 -> 1 | G8: 135 | I8: 249.99 | K8: =F8*G8 -> 135 | M8: =I8-G8 -> 114.99 | O8: =F8*I8 -> 249.99 | Q8: =F8*M8 -> 114.99
A9: BFSK-01 | C9: Télécommande Bipper | F9: ='Hardware O''Comptoir'!F9+'Hardware CuzCup'!F9 -> 1 | G9: 19 | I9: 24.99 | K9: =F9*G9 -> 19 | M9: =I9-G9 -> 5.99 | O9: =F9*I9 -> 24.99 | Q9: =F9*M9 -> 5.99
A10: BFSK-02 | C10: Base de charge Bipper | F10: ='Hardware O''Comptoir'!F10+'Hardware CuzCup'!F10 -> 4 | G10: 10 | I10: 19.99 | K10: =F10*G10 -> 40 | M10: =I10-G10 -> 9.99 | O10: =F10*I10 -> 79.96 | Q10: =F10*M10 -> 39.96
A11: BFSK-03 | C11: Biper FSK | F11: ='Hardware O''Comptoir'!F11+'Hardware CuzCup'!F11 -> 40 | G11: 3 | I11: 8.09 | K11: =F11*G11 -> 120 | M11: =I11-G11 -> 5.09 | O11: =F11*I11 -> 323.6 | Q11: =F11*M11 -> 203.6
A12: SN-1 | C12: SNIUP Licence | F12: ='Hardware O''Comptoir'!F12+'Hardware CuzCup'!F12+'Hardware SameSame'!F12 -> 7 | G12: 0 | I12: 79.99 | K12: =F12*G12 -> 0 | M12: =I12-G12 -> 79.99 | O12: =F12*I12 -> 559.93 | Q12: =F12*M12 -> 559.93
T15: One Shot | V15: =Q4+Q5+Q6+Q7+Q8+Q9+Q10+Q11 -> 10164.24
T16: Monthly | V16: =Q12 -> 559.93
A21: Hardware Investment
A23: Total Investment | C23: =SUM(K4:L12)+SUM('Hardware Stock'!K4:L11) -> 5734

Sheet Hardware Stock
A1: Hardware Stock
A3: Product Code | C3: Product Name | F3: Quantity | G3: Buy | I3: Sell | K3: Cost total | M3: Net value | O3: Total value | Q3: Total net value
A4: AKSP-21 | C4: Kiosk 21.5 | F4: 0 | G4: 500 | I4: 1699.99 | K4: =F4*G4 -> 0 | M4: =I4-G4 -> 1199.99 | O4: =F4*I4 -> 0 | Q4: =F4*M4 -> 0
A5: AKSP-27 | C5: Kiosk 27 | F5: 2 | G5: 680 | I5: 2100 | K5: =F5*G5 -> 1360 | M5: =I5-G5 -> 1420 | O5: =F5*I5 -> 4200 | Q5: =F5*M5 -> 2840
A6: AKSP-32 | C6: Kiosk 32 | F6: 0 | G6: 800 | I6: 2799.99 | K6: =F6*G6 -> 0 | M6: =I6-G6 -> 1999.99 | O6: =F6*I6 -> 0 | Q6: =F6*M6 -> 0
A7: PW-02 | C7: Imprimante | F7: 0 | G7: 80 | I7: 179.88 | K7: =F7*G7 -> 0 | M7: =I7-G7 -> 99.88 | O7: =F7*I7 -> 0 | Q7: =F7*M7 -> 0
A8: AT-11 | C8: Tablette 11 pouces | F8: 0 | G8: 135 | I8: 249.99 | K8: =F8*G8 -> 0 | M8: =I8-G8 -> 114.99 | O8: =F8*I8 -> 0 | Q8: =F8*M8 -> 0
A9: BFSK-01 | C9: Télécommande Bipper | F9: 0 | G9: 19 | I9: 24.99 | K9: =F9*G9 -> 0 | M9: =I9-G9 -> 5.99 | O9: =F9*I9 -> 0 | Q9: =F9*M9 -> 0
A10: BFSK-02 | C10: Base de charge Bipper | F10: 0 | G10: 10 | I10: 19.99 | K10: =F10*G10 -> 0 | M10: =I10-G10 -> 9.99 | O10: =F10*I10 -> 0 | Q10: =F10*M10 -> 0
A11: BFSK-03 | C11: Biper FSK | F11: 0 | G11: 3 | I11: 8.09 | K11: =F11*G11 -> 0 | M11: =I11-G11 -> 5.09 | O11: =F11*I11 -> 0 | Q11: =F11*M11 -> 0
A12: SN-1 | C12: SNIUP Licence | F12: 0 | G12: 0 | I12: 79.99 | K12: =F12*G12 -> 0 | M12: =I12-G12 -> 79.99 | O12: =F12*I12 -> 0 | Q12: =F12*M12 -> 0
T15: One Shot | V15: =SUM(Q4:R11) -> 2840
T16: Monthly | V16: =Q12 -> 0

Sheet Hardware SameSame
A1: Hardware
A3: Product Code | C3: Product Name | F3: Quantity | G3: Buy | I3: Sell | K3: Net value | M3: Total value | O3: Total net value
A4: AKSP-21 | C4: Kiosk 21.5 | F4: 0 | G4: 500 | I4: 1699.99 | K4: =I4-G4 -> 1199.99 | M4: =F4*I4 -> 0 | O4: =F4*K4 -> 0
A5: AKSP-27 | C5: Kiosk 27 | F5: 1 | G5: 680 | I5: 2100 | K5: =I5-G5 -> 1420 | M5: =F5*I5 -> 2100 | O5: =F5*K5 -> 1420
A6: AKSP-32 | C6: Kiosk 32 | F6: 0 | G6: 800 | I6: 2799.99 | K6: =I6-G6 -> 1999.99 | M6: =F6*I6 -> 0 | O6: =F6*K6 -> 0
A7: PW-02 | C7: Imprimante | F7: 0 | G7: 80 | I7: 179.88 | K7: =I7-G7 -> 99.88 | M7: =F7*I7 -> 0 | O7: =F7*K7 -> 0
A8: AT-11 | C8: Tablette 11 pouces | F8: 0 | G8: 135 | I8: 249.99 | K8: =I8-G8 -> 114.99 | M8: =F8*I8 -> 0 | O8: =F8*K8 -> 0
A9: BFSK-01 | C9: Télécommande Bipper | F9: 0 | G9: 19 | I9: 24.99 | K9: =I9-G9 -> 5.99 | M9: =F9*I9 -> 0 | O9: =F9*K9 -> 0
A10: BFSK-02 | C10: Base de charge Bipper | F10: 0 | G10: 10 | I10: 19.99 | K10: =I10-G10 -> 9.99 | M10: =F10*I10 -> 0 | O10: =F10*K10 -> 0
A11: BFSK-03 | C11: Biper FSK | F11: 0 | G11: 3 | I11: 8.09 | K11: =I11-G11 -> 5.09 | M11: =F11*I11 -> 0 | O11: =F11*K11 -> 0
A12: SN-1 | C12: SNIUP Licence | F12: 1 | G12: 0 | I12: 79.99 | K12: =I12-G12 -> 79.99 | M12: =F12*I12 -> 79.99 | O12: =F12*K12 -> 79.99
R15: One Shot | T15: =SUM(O4:P11) -> 1420
R16: Monthly | T16: =O12 -> 79.99

Sheet Hardware O'Comptoir
A1: Hardware
A3: Product Code | C3: Product Name | F3: Quantity | G3: Buy | I3: Sell | K3: Net value | M3: Total value | O3: Total net value
A4: AKSP-21 | C4: Kiosk 21.5 | F4: 2 | G4: 500 | I4: 1699.99 | K4: =I4-G4 -> 1199.99 | M4: =F4*I4 -> 3399.98 | O4: =F4*K4 -> 2399.98
A5: AKSP-27 | C5: Kiosk 27 | F5: 0 | G5: 680 | I5: 2100 | K5: =I5-G5 -> 1420 | M5: =F5*I5 -> 0 | O5: =F5*K5 -> 0
A6: AKSP-32 | C6: Kiosk 32 | F6: 2 | G6: 800 | I6: 2799.99 | K6: =I6-G6 -> 1999.99 | M6: =F6*I6 -> 5599.98 | O6: =F6*K6 -> 3999.98
A7: PW-02 | C7: Imprimante | F7: 2 | G7: 80 | I7: 179.88 | K7: =I7-G7 -> 99.88 | M7: =F7*I7 -> 359.76 | O7: =F7*K7 -> 199.76
A8: AT-11 | C8: Tablette 11 pouces | F8: 1 | G8: 135 | I8: 249.99 | K8: =I8-G8 -> 114.99 | M8: =F8*I8 -> 249.99 | O8: =F8*K8 -> 114.99
A9: BFSK-01 | C9: Télécommande Bipper | F9: 1 | G9: 19 | I9: 24.99 | K9: =I9-G9 -> 5.99 | M9: =F9*I9 -> 24.99 | O9: =F9*K9 -> 5.99
A10: BFSK-02 | C10: Base de charge Bipper | F10: 4 | G10: 10 | I10: 19.99 | K10: =I10-G10 -> 9.99 | M10: =F10*I10 -> 79.96 | O10: =F10*K10 -> 39.96
A11: BFSK-03 | C11: Biper FSK | F11: 40 | G11: 3 | I11: 8.09 | K11: =I11-G11 -> 5.09 | M11: =F11*I11 -> 323.6 | O11: =F11*K11 -> 203.6
A12: SN-1 | C12: SNIUP Licence | F12: 4 | G12: 0 | I12: 79.99 | K12: =I12-G12 -> 79.99 | M12: =F12*I12 -> 319.96 | O12: =F12*K12 -> 319.96
R15: One Shot | T15: =SUM(O4:P11) -> 6964.26
R16: Monthly | T16: =O12 -> 319.96

Sheet Hardware CuzCup
A1: Hardware
A3: Product Code | C3: Product Name | F3: Quantity | G3: Buy | I3: Sell | K3: Net value | M3: Total value | O3: Total net value
A4: AKSP-21 | C4: Kiosk 21.5 | F4: 1 | G4: 500 | I4: 1699.99 | K4: =I4-G4 -> 1199.99 | M4: =F4*I4 -> 1699.99 | O4: =F4*K4 -> 1199.99
A5: AKSP-27 | C5: Kiosk 27 | F5: 0 | G5: 680 | I5: 2100 | K5: =I5-G5 -> 1420 | M5: =F5*I5 -> 0 | O5: =F5*K5 -> 0
A6: AKSP-32 | C6: Kiosk 32 | F6: 1 | G6: 800 | I6: 2799.99 | K6: =I6-G6 -> 1999.99 | M6: =F6*I6 -> 2799.99 | O6: =F6*K6 -> 1999.99
A7: PW-02 | C7: Imprimante | F7: 0 | G7: 80 | I7: 179.88 | K7: =I7-G7 -> 99.88 | M7: =F7*I7 -> 0 | O7: =F7*K7 -> 0
A8: AT-11 | C8: Tablette 11 pouces | F8: 0 | G8: 135 | I8: 249.99 | K8: =I8-G8 -> 114.99 | M8: =F8*I8 -> 0 | O8: =F8*K8 -> 0
A9: BFSK-01 | C9: Télécommande Bipper | F9: 0 | G9: 19 | I9: 24.99 | K9: =I9-G9 -> 5.99 | M9: =F9*I9 -> 0 | O9: =F9*K9 -> 0
A10: BFSK-02 | C10: Base de charge Bipper | F10: 0 | G10: 10 | I10: 19.99 | K10: =I10-G10 -> 9.99 | M10: =F10*I10 -> 0 | O10: =F10*K10 -> 0
A11: BFSK-03 | C11: Biper FSK | F11: 0 | G11: 3 | I11: 8.09 | K11: =I11-G11 -> 5.09 | M11: =F11*I11 -> 0 | O11: =F11*K11 -> 0
A12: SN-1 | C12: SNIUP Licence | F12: 2 | G12: 0 | I12: 79.99 | K12: =I12-G12 -> 79.99 | M12: =F12*I12 -> 159.98 | O12: =F12*K12 -> 159.98
R15: One Shot | T15: =SUM(O4:P11) -> 3199.98
R16: Monthly | T16: =M12 -> 159.98

Sheet Product Gain Calculator
A1: Produit | E1: Quantité | F1: Prix d'achat Unité | I1: Kilo Unité | K1: Prix Total | M1: Kilo Total | O1: Lon | P1: Lar | Q1: Hau | R1: Total Volumetrique | T1: Prix par kilo | V1: Cout logistique Unité | X1: Cout logistique Total | Z1: Prix de revient unité | AB1: Prix de revient total | AD1: Prix de vente unité | AF1: Prix de vente total | AH1: Benefice Net | AJ1: Investissement | AL1: Benefice Net % | AN1: Pourcent investisseurs | AP1: Retour investisseurs | AR1: Benefice Net
A2: Projecteur | E2: 4 | F2: 125 | I2: 3.85 | K2: =E2*F2 -> 500 | M2: =E2*I2 -> 15.4 | O2: 30 | P2: 66 | Q2: 57 | R2: =O2*P2*Q2/5000 -> 22.572 | T2: 7.5 | V2: =X2/E2 -> 42.3225 | X2: =R2*T2 -> 169.29 | Z2: =F2+V2 -> 167.3225 | AB2: =(K2+X2) -> 669.29 | AD2: 350 | AF2: =AD2*E2 -> 1400 | AH2: =AF2-AB2 -> 730.71 | AJ2: =AB2 -> 669.29 | AL2: =(AF2-AJ2)/AJ2 -> 1.0917689 | AN2: 0.2 | AP2: =AH2*AN2 -> 146.142
A3: Airpods | E3: 50 | F3: 7.85 | I3: 0.4 | K3: =E3*F3 -> 392.5 | M3: =E3*I3 -> 20 | R3: 18 | T3: 7.5 | V3: =X3/E3 -> 2.7 | X3: =R3*T3 -> 135 | Z3: =F3+V3 -> 10.55 | AB3: =(K3+X3) -> 527.5 | AD3: 50 | AF3: =AD3*E3 -> 2500 | AH3: =AF3-AB3 -> 1972.5 | AJ3: =AB3 -> 527.5 | AL3: =(AF3-AJ3)/AJ3 -> 3.7393365 | AN3: 0.2 | AP3: =AH3*AN3 -> 394.5
A4: Serrure | E4: 8 | F4: 25.9 | K4: =E4*F4 -> 207.2 | R4: 24.5 | T4: 7.5 | V4: =X4/E4 -> 22.96875 | X4: =R4*T4 -> 183.75 | Z4: =F4+V4 -> 48.86875 | AB4: =(K4+X4) -> 390.95 | AD4: 80 | AF4: =AD4*E4 -> 640 | AH4: =AF4-AB4 -> 249.05 | AJ4: =AB4 -> 390.95 | AL4: =(AF4-AJ4)/AJ4 -> 0.63703798 | AN4: 0.2 | AP4: =AH4*AN4 -> 49.81
A5: Protection écran | E5: 2000 | F5: 0.3 | I5: 0.1 | K5: =E5*F5 -> 600 | M5: 20 | R5: 25 | T5: 7.5 | V5: =X5/E5 -> 0.09375 | X5: =R5*T5 -> 187.5 | Z5: =F5+V5 -> 0.39375 | AB5: =(K5+X5) -> 787.5 | AD5: 1 | AF5: =AD5*E5 -> 2000 | AH5: =AF5-AB5 -> 1212.5 | AJ5: =AB5 -> 787.5 | AL5: =(AF5-AJ5)/AJ5 -> 1.5396825 | AN5: 0.2 | AP5: =AH5*AN5 -> 242.5
A6: Shoes | E6: 14 | F6: 25 | I6: 1.14 | K6: =E6*F6 -> 350 | M6: 16 | R6: 16 | T6: 7.5 | V6: =X6/E6 -> 8.5714286 | X6: =R6*T6 -> 120 | Z6: =F6+V6 -> 33.571429 | AB6: =(K6+X6) -> 470 | AD6: 60 | AF6: =AD6*E6 -> 840 | AH6: =AF6-AB6 -> 370 | AJ6: =AB6 -> 470 | AL6: =(AF6-AJ6)/AJ6 -> 0.78723404 | AN6: 0.2
